<?xml version="1.0" encoding="utf-8" ?>
<dwsync>
<file name="PHPExcel_Reader_CSV.html" server="186.10.233.98" local="131810220000000000" remote="131810220000000000" />
<file name="PHPExcel_Reader_DefaultReadFilter.html" server="186.10.233.98" local="131810220000000000" remote="131810220000000000" />
<file name="PHPExcel_Reader_Excel2003XML.html" server="186.10.233.98" local="131810220000000000" remote="131810220000000000" />
<file name="PHPExcel_Reader_Excel2007.html" server="186.10.233.98" local="131810220000000000" remote="131810220000000000" />
<file name="PHPExcel_Reader_Gnumeric.html" server="186.10.233.98" local="131810220000000000" remote="131810220000000000" />
<file name="PHPExcel_Reader_IReadFilter.html" server="186.10.233.98" local="131810220000000000" remote="131810220000000000" />
<file name="PHPExcel_Reader_IReader.html" server="186.10.233.98" local="131810220000000000" remote="131810220000000000" />
<file name="PHPExcel_Reader_OOCalc.html" server="186.10.233.98" local="131810220000000000" remote="131810220000000000" />
<file name="PHPExcel_Reader_SYLK.html" server="186.10.233.98" local="131810220000000000" remote="131810220000000000" />
<file name="_PHPExcel---Reader---CSV.php.html" server="186.10.233.98" local="131810220000000000" remote="131810220000000000" />
<file name="_PHPExcel---Reader---DefaultReadFilter.php.html" server="186.10.233.98" local="131810220000000000" remote="131810220000000000" />
<file name="_PHPExcel---Reader---Excel2003XML.php.html" server="186.10.233.98" local="131810220000000000" remote="131810220000000000" />
<file name="_PHPExcel---Reader---Excel2007.php.html" server="186.10.233.98" local="131810220000000000" remote="131810220000000000" />
<file name="_PHPExcel---Reader---Gnumeric.php.html" server="186.10.233.98" local="131810220000000000" remote="131810220000000000" />
<file name="_PHPExcel---Reader---IReadFilter.php.html" server="186.10.233.98" local="131810220000000000" remote="131810220000000000" />
<file name="_PHPExcel---Reader---IReader.php.html" server="186.10.233.98" local="131810220000000000" remote="131810220000000000" />
<file name="_PHPExcel---Reader---OOCalc.php.html" server="186.10.233.98" local="131810220000000000" remote="131810220000000000" />
<file name="_PHPExcel---Reader---SYLK.php.html" server="186.10.233.98" local="131810220000000000" remote="131810220000000000" />
</dwsync>